pybo/__init__.py
pybo/cli.py
pybo/hfr_cqlr_converter.py
pybo/monlam2wordlist.py
pybo/untokenize.py
pybo/corpus/__init__.py
pybo/corpus/parse_corrected.py
pybo/corpus/word_cleanup.py
pybo/pipeline/__init__.py
pybo/pipeline/pipes.py
pybo/rdr/__init__.py
pybo/rdr/rdr.py
pybo/rdr/rdr_2_replace_matcher.py
pybo/segmentation_rule/__init__.py
pybo/segmentation_rule/make_rule.py
pybo/segmentation_rule/pipeline.py
pybo/utils/__init__.py
pybo/utils/bo_sorted.py
pybo/utils/profile_entries.py
pybo/utils/profile_report.py
pybo/utils/regex_batch_apply.py
pybo-0.8.0.dist-info/LICENSE
pybo-0.8.0.dist-info/METADATA
pybo-0.8.0.dist-info/WHEEL
pybo-0.8.0.dist-info/entry_points.txt
pybo-0.8.0.dist-info/top_level.txt
pybo-0.8.0.dist-info/RECORD
