Metadata-Version: 2.1
Name: pybo
Version: 0.8.0
Summary: Python utils for processing Tibetan
Home-page: https://github.com/Esukhia/pybo
Author: Esukhia development team
Author-email: esukhiadev@gmail.com
License: Apache2
Project-URL: Source, https://github.com/Esukhia/pybo
Project-URL: Tracker, https://github.com/Esukhia/pybo/issues
Keywords: nlp computational_linguistics search ngrams language_models linguistics toolkit tibetan
Platform: UNKNOWN
Classifier: Development Status :: 3 - Alpha
Classifier: Topic :: Text Processing :: Linguistic
Classifier: Programming Language :: Python :: 3
Classifier: Operating System :: OS Independent
Classifier: Intended Audience :: Developers
Classifier: Intended Audience :: Science/Research
Classifier: License :: OSI Approved :: Apache Software License
Classifier: Natural Language :: Tibetan
Requires-Python: >=3.6
